neural_semigroups/__init__.py
neural_semigroups/associator_loss.py
neural_semigroups/constant_baseline.py
neural_semigroups/constants.py
neural_semigroups/cyclic_group.py
neural_semigroups/datasets/__init__.py
neural_semigroups/datasets/mace4_semigroups_dataset.py
neural_semigroups/datasets/random_dataset.py
neural_semigroups/datasets/semigroups_dataset.py
neural_semigroups/datasets/smallsemi_dataset.py
neural_semigroups/denoising_autoencoder.py
neural_semigroups/generate_data_with_mace4.py
neural_semigroups/magma.py
neural_semigroups/precise_guess_loss.py
neural_semigroups/py.typed
neural_semigroups/training_helpers.py
neural_semigroups/utils.py
neural_semigroups-0.6.3.dist-info/LICENSE
neural_semigroups-0.6.3.dist-info/WHEEL
neural_semigroups-0.6.3.dist-info/METADATA
neural_semigroups-0.6.3.dist-info/RECORD
