Metadata-Version: 2.1
Name: neural-semigroups
Version: 0.6.3
Summary: Neural networks powered research of semigroups
Home-page: https://github.com/inpefess/neural-semigroups
License: Apache-2.0
Author: Boris Shminke
Author-email: boris@shminke.ml
Requires-Python: >=3.7.1,<3.10
Classifier: Development Status :: 7 - Inactive
Classifier: Environment :: Console
Classifier: Intended Audience :: Science/Research
Classifier: License :: OSI Approved :: Apache Software License
Classifier: Natural Language :: English
Classifier: Operating System :: OS Independent
Classifier: Programming Language :: Python :: 3
Classifier: Programming Language :: Python :: 3.7
Classifier: Programming Language :: Python :: 3.8
Classifier: Programming Language :: Python :: 3.9
Classifier: Topic :: Scientific/Engineering :: Artificial Intelligence
Classifier: Typing :: Typed
Requires-Dist: pytorch-ignite
Requires-Dist: tensorboard
Requires-Dist: torch
Requires-Dist: tqdm
Project-URL: Documentation, https://neural-semigroups.readthedocs.io
Project-URL: Repository, https://github.com/inpefess/neural-semigroups
